async_pyserial/__init__.py
async_pyserial/async_pyserial_core.cp311-win_amd64.pyd
async_pyserial/async_pyserial_core.pyi
async_pyserial/backend.py
async_pyserial/common.py
async_pyserial/native_serialport.py
async_pyserial-0.2.4.dist-info/licenses/LICENSE
async_pyserial-0.2.4.dist-info/METADATA
async_pyserial-0.2.4.dist-info/WHEEL
async_pyserial-0.2.4.dist-info/top_level.txt
async_pyserial-0.2.4.dist-info/RECORD
