Metadata-Version: 2.4
Name: async_pyserial
Version: 0.2.4
Summary: Python bindings for a C++ serial port library
Author: Neil Lei
Author-email: Neil Lei <qwe17235@gmail.com>
Project-URL: Homepage, https://github.com/Lei-k/async-pyserial/tree/main
Project-URL: Issues, https://github.com/Lei-k/async-pyserial/issues
Classifier: Programming Language :: Python :: 3
Classifier: Programming Language :: Python :: 3.8
Classifier: Programming Language :: Python :: 3.9
Classifier: Programming Language :: Python :: 3.10
Classifier: Programming Language :: Python :: 3.11
Classifier: Programming Language :: Python :: 3.12
Classifier: License :: OSI Approved :: MIT License
Classifier: Operating System :: Microsoft :: Windows
Classifier: Operating System :: POSIX
Classifier: Operating System :: POSIX :: Linux
Classifier: Operating System :: MacOS
Classifier: Operating System :: MacOS :: MacOS X
Classifier: Operating System :: POSIX :: BSD
Requires-Python: >=3.8
License-File: LICENSE
Dynamic: author
Dynamic: license-file
